kinisi/__init__.py
kinisi/analyze.py
kinisi/analyzer.py
kinisi/arrhenius.py
kinisi/ase.py
kinisi/conductivity_analyzer.py
kinisi/diffusion.py
kinisi/diffusion_analyzer.py
kinisi/displacement.py
kinisi/due.py
kinisi/fitting.py
kinisi/jump_diffusion_analyzer.py
kinisi/mdanalysis.py
kinisi/parser.py
kinisi/pymatgen.py
kinisi/samples.py
kinisi/yeh_hummer.py
kinisi/tests/__init__.py
kinisi/tests/test_analyzer.py
kinisi/tests/test_arrhenius.py
kinisi/tests/test_ase.py
kinisi/tests/test_conductivity_analyzer.py
kinisi/tests/test_diffusion.py
kinisi/tests/test_diffusion_analyzer.py
kinisi/tests/test_displacement.py
kinisi/tests/test_jump_diffusion_analyzer.py
kinisi/tests/test_mdanalysis.py
kinisi/tests/test_parser.py
kinisi/tests/test_pymatgen.py
kinisi/tests/test_samples.py
kinisi/tests/test_yeh_hummer.py
kinisi/tests/inputs/LiPS.exyz
kinisi/tests/inputs/LiPS_msd.npy
kinisi/tests/inputs/example_Analyzer.h5
kinisi/tests/inputs/example_ConductivityAnalyzer.h5
kinisi/tests/inputs/example_DiffusionAnalyzer.h5
kinisi/tests/inputs/example_JumpDiffusionAnalyzer.h5
kinisi/tests/inputs/example_LAMMPS.data
kinisi/tests/inputs/example_LAMMPS.dcd
kinisi/tests/inputs/example_LAMMPS_center.data
kinisi/tests/inputs/example_LAMMPS_center.traj
kinisi/tests/inputs/example_LAMMPS_drift.data
kinisi/tests/inputs/example_LAMMPS_drift.traj
kinisi/tests/inputs/example_XDATCAR.gz
kinisi/tests/inputs/example_ase.traj
kinisi/tests/inputs/example_ase_center.traj
kinisi/tests/inputs/example_ase_drift.traj
kinisi/tests/inputs/example_center.XDATCAR
kinisi/tests/inputs/example_drift.XDATCAR
kinisi/tests/inputs/example_drift.h5
kinisi/tests/inputs/example_msd2.hdf5
kinisi-2.0.4.dist-info/METADATA
kinisi-2.0.4.dist-info/WHEEL
kinisi-2.0.4.dist-info/licenses/LICENSE
kinisi-2.0.4.dist-info/RECORD
