Metadata-Version: 2.4
Name: kinisi
Version: 2.0.4
Summary: Efficient estimation of diffusion processes from molecular dynamics.
Project-URL: homepage, https://github.com/bjmorgan/kinisi
Project-URL: documentation, https://kinisi.rtfd.io
Author-email: "Andrew R. McCluskey" <andrew.mccluskey@bristol.ac.uk>, "Benjamin J. Morgan" <b.j.morgan@bath.ac.uk>
Maintainer-email: "Andrew R. McCluskey" <andrew.mccluskey@bristol.ac.uk>, "Benjamin J. Morgan" <b.j.morgan@bath.ac.uk>
License-Expression: MIT
License-File: LICENSE
Classifier: Development Status :: 4 - Beta
Classifier: Intended Audience :: Science/Research
Classifier: License :: OSI Approved :: MIT License
Classifier: Natural Language :: English
Classifier: Operating System :: OS Independent
Classifier: Programming Language :: Python :: 3.8
Classifier: Programming Language :: Python :: 3.9
Classifier: Programming Language :: Python :: 3.10
Classifier: Programming Language :: Python :: 3.11
Classifier: Topic :: Scientific/Engineering
Classifier: Topic :: Scientific/Engineering :: Chemistry
Classifier: Topic :: Scientific/Engineering :: Physics
Requires-Python: >=3.10
Requires-Dist: bs4>=0.0.2
Requires-Dist: dynesty>=2.1.5
Requires-Dist: emcee>=3.1.6
Requires-Dist: numpy>=2.0.0
Requires-Dist: scikit-learn>=1.5.0
Requires-Dist: scipp>=24.8.0
Requires-Dist: scipy>=1.9.3
Requires-Dist: statsmodels>=0.14.0
Requires-Dist: tqdm
Requires-Dist: uncertainties>=3.2.3
Provides-Extra: dev
Requires-Dist: ase; extra == 'dev'
Requires-Dist: h5py; extra == 'dev'
Requires-Dist: mdanalysis>=2.8.0; extra == 'dev'
Requires-Dist: pre-commit; extra == 'dev'
Requires-Dist: pymatgen; extra == 'dev'
Requires-Dist: pytest; extra == 'dev'
Requires-Dist: pytest-cov; extra == 'dev'
Requires-Dist: ruff; extra == 'dev'
Provides-Extra: docs
Requires-Dist: ase; extra == 'docs'
Requires-Dist: corner; extra == 'docs'
Requires-Dist: h5py; extra == 'docs'
Requires-Dist: ipykernel; extra == 'docs'
Requires-Dist: mdanalysis>=2.8.0; extra == 'docs'
Requires-Dist: myst-parser; extra == 'docs'
Requires-Dist: nbsphinx; extra == 'docs'
Requires-Dist: pydata-sphinx-theme; extra == 'docs'
Requires-Dist: pymatgen; extra == 'docs'
Requires-Dist: pymatgen-analysis-diffusion; extra == 'docs'
Requires-Dist: sphinx-autodoc-typehints; extra == 'docs'
Requires-Dist: tidynamics; extra == 'docs'
